pyDOE3/__init__.py
pyDOE3/_version.py
pyDOE3/build_regression_matrix.py
pyDOE3/doe_box_behnken.py
pyDOE3/doe_composite.py
pyDOE3/doe_cranley_patterson_shift.py
pyDOE3/doe_doehlert.py
pyDOE3/doe_factorial.py
pyDOE3/doe_fold.py
pyDOE3/doe_gsd.py
pyDOE3/doe_halton.py
pyDOE3/doe_korobov.py
pyDOE3/doe_lhs.py
pyDOE3/doe_plackett_burman.py
pyDOE3/doe_random_k_means.py
pyDOE3/doe_random_uniform.py
pyDOE3/doe_rank1.py
pyDOE3/doe_repeat_center.py
pyDOE3/doe_saltelli.py
pyDOE3/doe_sobol.py
pyDOE3/doe_sparse_grid.py
pyDOE3/doe_star.py
pyDOE3/doe_taguchi.py
pyDOE3/doe_union.py
pyDOE3/doe_vanilla_morris.py
pyDOE3/utils.py
pyDOE3/var_regression_matrix.py
pyDOE3/doe_optimal/__init__.py
pyDOE3/doe_optimal/algorithms.py
pyDOE3/doe_optimal/criterion.py
pyDOE3/doe_optimal/efficiency.py
pyDOE3/doe_optimal/model.py
pyDOE3/doe_optimal/optimal.py
pyDOE3/doe_optimal/utils.py
pyDOE3/grid_designs/__init__.py
pyDOE3/grid_designs/doe_sukharev.py
pyDOE3/orthogonal_arrays/L_12_2_11.oa
pyDOE3/orthogonal_arrays/L_16_2_15.oa
pyDOE3/orthogonal_arrays/L_16_4_5.oa
pyDOE3/orthogonal_arrays/L_18_6_1_3_6.oa
pyDOE3/orthogonal_arrays/L_25_5_6.oa
pyDOE3/orthogonal_arrays/L_27_2_1_3_12.oa
pyDOE3/orthogonal_arrays/L_32_2_1_4_9.oa
pyDOE3/orthogonal_arrays/L_32_2_31.oa
pyDOE3/orthogonal_arrays/L_36_3_23.oa
pyDOE3/orthogonal_arrays/L_4_2_3.oa
pyDOE3/orthogonal_arrays/L_50_2_1_5_11.oa
pyDOE3/orthogonal_arrays/L_54_2_1_3_25.oa
pyDOE3/orthogonal_arrays/L_64_2_31.oa
pyDOE3/orthogonal_arrays/L_64_4_21.oa
pyDOE3/orthogonal_arrays/L_81_3_40.oa
pyDOE3/orthogonal_arrays/L_8_2_7.oa
pyDOE3/orthogonal_arrays/L_9_3_4.oa
pyDOE3/orthogonal_arrays/__init__.py
pyDOE3/orthogonal_arrays/orthogonal_arrays.py
pydoe3-1.6.0.dist-info/METADATA
pydoe3-1.6.0.dist-info/WHEEL
pydoe3-1.6.0.dist-info/licenses/LICENSE
pydoe3-1.6.0.dist-info/RECORD
