Metadata-Version: 2.4
Name: pyDOE3
Version: 1.6.0
Summary: Design of experiments for Python
Project-URL: source, https://github.com/relf/pyDOE3
Author-email: Rémi Lafage <remi.lafage@onera.fr>
License-Expression: BSD-3-Clause
License-File: LICENSE
Keywords: DOE,design of experiments,experimental design,optimal design,optimization,python,sparse grids,statistics,taguchi design
Classifier: Development Status :: 5 - Production/Stable
Classifier: Intended Audience :: Education
Classifier: Intended Audience :: Science/Research
Classifier: License :: OSI Approved :: BSD License
Classifier: Operating System :: OS Independent
Classifier: Programming Language :: Python
Classifier: Programming Language :: Python :: 3.9
Classifier: Programming Language :: Python :: 3.10
Classifier: Programming Language :: Python :: 3.11
Classifier: Programming Language :: Python :: 3.12
Classifier: Topic :: Education
Classifier: Topic :: Scientific/Engineering
Classifier: Topic :: Scientific/Engineering :: Mathematics
Classifier: Topic :: Scientific/Engineering :: Physics
Classifier: Topic :: Software Development
Classifier: Topic :: Software Development :: Libraries
Classifier: Topic :: Software Development :: Libraries :: Python Modules
Classifier: Topic :: Utilities
Requires-Dist: numpy
Requires-Dist: scipy
